django_rest_framework_client-0.12.0.dist-info/METADATA
django_rest_framework_client-0.12.0.dist-info/WHEEL
django_rest_framework_client-0.12.0.dist-info/entry_points.txt
django_rest_framework_client-0.12.0.dist-info/licenses/LICENSE
drf_client/__init__.py
drf_client/connection.py
drf_client/exceptions.py
drf_client/helpers/base_facade.py
drf_client/helpers/base_main.py
django_rest_framework_client-0.12.0.dist-info/RECORD
