Metadata-Version: 2.1
Name: django-rest-framework-client
Version: 0.12.0
Summary: Python client for a DjangoRestFramework based web site
Keywords: django,djangorestframework,drf,rest-client
Author-Email: David Karchmer <dkarchmer@gmail.com>
License: The MIT License (MIT)
Classifier: Development Status :: 4 - Beta
Classifier: License :: OSI Approved :: MIT License
Classifier: Operating System :: OS Independent
Classifier: Programming Language :: Python
Classifier: Programming Language :: Python :: 3
Classifier: Programming Language :: Python :: 3.10
Classifier: Programming Language :: Python :: 3.11
Classifier: Programming Language :: Python :: 3.9
Classifier: Programming Language :: Python :: Implementation :: PyPy
Classifier: Topic :: Software Development :: Libraries :: Python Modules
Project-URL: Homepage, https://github.com/dkarchmer/django-rest-framework-client
Project-URL: Repository, https://github.com/dkarchmer/django-rest-framework-client
Requires-Python: <4,>=3.10
Requires-Dist: requests
Requires-Dist: httpx>=0.28.1
Requires-Dist: respx>=0.22.0
Provides-Extra: dev
Requires-Dist: pytest>=8.3.2; extra == "dev"
Requires-Dist: ruff>=0.5.5; extra == "dev"
Requires-Dist: coverage>=7.6.0; extra == "dev"
Requires-Dist: mock>=5.1.0; extra == "dev"
Requires-Dist: requests-mock>=1.12.1; extra == "dev"
Requires-Dist: pre-commit>=3.7.1; extra == "dev"
Requires-Dist: setuptools>=78.1.0; extra == "dev"
Requires-Dist: twine>=6.1.0; extra == "dev"
Requires-Dist: wheel>=0.46.1; extra == "dev"
